DaimaZhengjiZhidaoFix1/README.md
DaimaZhengjiZhidaoFix1/__init__.py
DaimaZhengjiZhidaoFix1/__main__.py
DaimaZhengjiZhidaoFix1/file.epub
DaimaZhengjiZhidaoFix1/index.html
DaimaZhengjiZhidaoFix1/css/__init__.py
DaimaZhengjiZhidaoFix1/css/annotations.css
DaimaZhengjiZhidaoFix1/css/main.css
DaimaZhengjiZhidaoFix1/css/normalize.css
DaimaZhengjiZhidaoFix1/css/popup.css
DaimaZhengjiZhidaoFix1/font/__init__.py
DaimaZhengjiZhidaoFix1/font/fontello.eot
DaimaZhengjiZhidaoFix1/font/fontello.svg
DaimaZhengjiZhidaoFix1/font/fontello.ttf
DaimaZhengjiZhidaoFix1/font/fontello.woff
DaimaZhengjiZhidaoFix1/img/__init__.py
DaimaZhengjiZhidaoFix1/img/annotator-glyph-sprite.png
DaimaZhengjiZhidaoFix1/img/annotator-icon-sprite.png
DaimaZhengjiZhidaoFix1/img/apple-touch-icon.png
DaimaZhengjiZhidaoFix1/img/cancelfullscreen.png
DaimaZhengjiZhidaoFix1/img/close.png
DaimaZhengjiZhidaoFix1/img/fullscreen.png
DaimaZhengjiZhidaoFix1/img/loader.gif
DaimaZhengjiZhidaoFix1/img/menu-icon.png
DaimaZhengjiZhidaoFix1/img/save.png
DaimaZhengjiZhidaoFix1/img/saved.png
DaimaZhengjiZhidaoFix1/img/settings-s.png
DaimaZhengjiZhidaoFix1/img/settings.png
DaimaZhengjiZhidaoFix1/img/star.png
DaimaZhengjiZhidaoFix1/js/__init__.py
DaimaZhengjiZhidaoFix1/js/epub.js
DaimaZhengjiZhidaoFix1/js/epub.min.js
DaimaZhengjiZhidaoFix1/js/epub.min.map
DaimaZhengjiZhidaoFix1/js/hooks.min.js
DaimaZhengjiZhidaoFix1/js/hooks.min.map
DaimaZhengjiZhidaoFix1/js/reader.js
DaimaZhengjiZhidaoFix1/js/reader.js.map
DaimaZhengjiZhidaoFix1/js/reader.min.js
DaimaZhengjiZhidaoFix1/js/reader.min.map
DaimaZhengjiZhidaoFix1/js/hooks/__init__.py
DaimaZhengjiZhidaoFix1/js/hooks/extensions/__init__.py
DaimaZhengjiZhidaoFix1/js/hooks/extensions/highlight.js
DaimaZhengjiZhidaoFix1/js/libs/__init__.py
DaimaZhengjiZhidaoFix1/js/libs/jquery.min.js
DaimaZhengjiZhidaoFix1/js/libs/localforage.min.js
DaimaZhengjiZhidaoFix1/js/libs/screenfull.js
DaimaZhengjiZhidaoFix1/js/libs/screenfull.min.js
DaimaZhengjiZhidaoFix1/js/libs/zip.min.js
daima_zhengji_zhidao_fix1-2025.3.24.0.dist-info/METADATA
daima_zhengji_zhidao_fix1-2025.3.24.0.dist-info/WHEEL
daima_zhengji_zhidao_fix1-2025.3.24.0.dist-info/entry_points.txt
daima_zhengji_zhidao_fix1-2025.3.24.0.dist-info/top_level.txt
daima_zhengji_zhidao_fix1-2025.3.24.0.dist-info/RECORD
